{"date": "2026-05-29", "snapshots": [{"ts": "2026-05-29T00:00:33.599299Z", "coins": [{"id": "bonk", "symbol": "BONK", "name": "Bonk", "mcap_rank": 108, "score": 0, "price_usd": 5.448598332718598e-06, "pct_24h": -4.832524057405916}, {"id": "aptos", "symbol": "APT", "name": "Aptos", "mcap_rank": 82, "score": 1, "price_usd": 0.9370776739108236, "pct_24h": -1.118841372486366}, {"id": "stellar", "symbol": "XLM", "name": "Stellar", "mcap_rank": 17, "score": 2, "price_usd": 0.20155488158909354, "pct_24h": 23.945775205586415}, {"id": "pudgy-penguins", "symbol": "PENGU", "name": "Pudgy Penguins", "mcap_rank": 106, "score": 3, "price_usd": 0.0077132341097465055, "pct_24h": -5.1635966347851605}, {"id": "hyperliquid", "symbol": "HYPE", "name": "Hyperliquid", "mcap_rank": 11, "score": 4, "price_usd": 61.64596305909409, "pct_24h": 6.71124373866145}, {"id": "ondo-finance", "symbol": "ONDO", "name": "Ondo", "mcap_rank": 48, "score": 5, "price_usd": 0.3676141090392459, "pct_24h": -4.595010266389058}, {"id": "venice-token", "symbol": "VVV", "name": "Venice Token", "mcap_rank": 84, "score": 6, "price_usd": 16.09717804873744, "pct_24h": -2.6543679152488764}, {"id": "allora", "symbol": "ALLO", "name": "Allora", "mcap_rank": 568, "score": 7, "price_usd": 0.16371326026975394, "pct_24h": 79.7657482450409}, {"id": "bitcoin", "symbol": "BTC", "name": "Bitcoin", "mcap_rank": 1, "score": 8, "price_usd": 73450.65340411241, "pct_24h": -1.228998331587067}, {"id": "solstice", "symbol": "SLX", "name": "Solstice", "mcap_rank": 476, "score": 9, "price_usd": 0.20908416423412676, "pct_24h": 5.902503358166773}, {"id": "lab", "symbol": "LAB", "name": "LAB", "mcap_rank": 132, "score": 10, "price_usd": 4.324637207894126, "pct_24h": -3.683445767640529}, {"id": "sui", "symbol": "SUI", "name": "Sui", "mcap_rank": 31, "score": 11, "price_usd": 0.9272965203697345, "pct_24h": -3.3213437027824546}, {"id": "zcash", "symbol": "ZEC", "name": "Zcash", "mcap_rank": 14, "score": 12, "price_usd": 545.3610551113424, "pct_24h": 0.5924150858449938}, {"id": "ethereum", "symbol": "ETH", "name": "Ethereum", "mcap_rank": 2, "score": 13, "price_usd": 2004.4656237385914, "pct_24h": -0.8865003590046704}, {"id": "fetch-ai", "symbol": "FET", "name": "Artificial Superintelligence Alliance", "mcap_rank": 99, "score": 14, "price_usd": 0.23025395192931383, "pct_24h": -4.488974659778839}], "nfts": [{"id": "normies", "name": "Normies", "symbol": "NORMIES", "contract": 102126225, "score": 0, "native_currency": "eth", "floor_native": 0.61999999, "floor_usd": "0.62 ETH", "floor_24h_pct_native": 19.43142927350929, "h24_volume": "74.77 ETH", "h24_avg_sale_price": "0.73 ETH"}, {"id": "meebits", "name": "Meebits", "symbol": "\u2687", "contract": 28, "score": 1, "native_currency": "eth", "floor_native": 0.3938999, "floor_usd": "0.39 ETH", "floor_24h_pct_native": 6.182132264205171, "h24_volume": "5.71 ETH", "h24_avg_sale_price": "0.44 ETH"}, {"id": "ordinal-maxi-biz-omb", "name": "Ordinal Maxi Biz (OMB)", "symbol": "OMB", "contract": 3256, "score": 2, "native_currency": "btc", "floor_native": 0.0175, "floor_usd": "0.018 BTC", "floor_24h_pct_native": 3.11180681057578, "h24_volume": "0.34 BTC", "h24_avg_sale_price": "0.11 BTC"}, {"id": "bitcoin-shrooms", "name": "Bitcoin Shrooms", "symbol": "BITCOINSHROOMS", "contract": 4161, "score": 3, "native_currency": "btc", "floor_native": 0.335, "floor_usd": "0.34 BTC", "floor_24h_pct_native": 1.596278246543891, "h24_volume": "0.31 BTC", "h24_avg_sale_price": "0.31 BTC"}, {"id": "lilpudgys", "name": "Lil Pudgys", "symbol": "LilPudgys", "contract": 229, "score": 4, "native_currency": "eth", "floor_native": 0.488, "floor_usd": "0.49 ETH", "floor_24h_pct_native": 0.7415947612703104, "h24_volume": "24.64 ETH", "h24_avg_sale_price": "0.48 ETH"}, {"id": "moonbirds", "name": "Moonbirds", "symbol": "MOONBIRD", "contract": 349, "score": 5, "native_currency": "eth", "floor_native": 0.736585, "floor_usd": "0.74 ETH", "floor_24h_pct_native": 0.511878732613164, "h24_volume": "9.93 ETH", "h24_avg_sale_price": "0.76 ETH"}, {"id": "milady-maker", "name": "Milady Maker", "symbol": "MIL", "contract": 317, "score": 6, "native_currency": "eth", "floor_native": 1.379999, "floor_usd": "1.38 ETH", "floor_24h_pct_native": -0.1516876658667419, "h24_volume": "13.35 ETH", "h24_avg_sale_price": "1.33 ETH"}], "categories": [{"id": 82, "name": "Derivatives", "slug": "decentralized-derivatives", "score": 0, "coins_count": "121", "mcap_1h_change": 0.7365814503638028, "mcap": 15637843569.508707, "total_volume": 1222716795.8696308, "mcap_24h_change_usd": 2.793377660918205}, {"id": 9, "name": "Decentralized Exchange (DEX)", "slug": "decentralized-exchange", "score": 1, "coins_count": "345", "mcap_1h_change": 0.7322324387666234, "mcap": 23555394456.943718, "total_volume": 1932701751.5334487, "mcap_24h_change_usd": 0.5104969059176869}, {"id": 62, "name": "Analytics", "slug": "analytics", "score": 2, "coins_count": "171", "mcap_1h_change": 0.6659398931732805, "mcap": 1960024177.220586, "total_volume": 348858202.6430069, "mcap_24h_change_usd": -5.030263306053714}, {"id": 20774, "name": "IP Meme", "slug": "ip-meme", "score": 3, "coins_count": "31", "mcap_1h_change": 0.6368317714034111, "mcap": 853408698.4223322, "total_volume": 179509946.79048938, "mcap_24h_change_usd": -7.856042677582144}, {"id": 314, "name": "Layer 0 (L0)", "slug": "layer-0-l0", "score": 4, "coins_count": "17", "mcap_1h_change": 0.5707297832524586, "mcap": 5080547417.853564, "total_volume": 382696072.092917, "mcap_24h_change_usd": -2.8557735885493742}, {"id": 107, "name": "Launchpad", "slug": "launchpad", "score": 5, "coins_count": "198", "mcap_1h_change": 0.5572912606354787, "mcap": 3428587285.1847258, "total_volume": 429746491.5329089, "mcap_24h_change_usd": -6.1263907017840635}]}, {"ts": "2026-05-29T00:06:58.614568Z", "coins": [{"id": "bonk", "symbol": "BONK", "name": "Bonk", "mcap_rank": 108, "score": 0, "price_usd": 5.450005323138718e-06, "pct_24h": -5.132973072053007}, {"id": "aptos", "symbol": "APT", "name": "Aptos", "mcap_rank": 82, "score": 1, "price_usd": 0.9389845971374696, "pct_24h": -1.0916993510153898}, {"id": "stellar", "symbol": "XLM", "name": "Stellar", "mcap_rank": 17, "score": 2, "price_usd": 0.20252360864662397, "pct_24h": 23.520802382509608}, {"id": "hyperliquid", "symbol": "HYPE", "name": "Hyperliquid", "mcap_rank": 11, "score": 3, "price_usd": 61.55544644668692, "pct_24h": 6.632618063426415}, {"id": "venice-token", "symbol": "VVV", "name": "Venice Token", "mcap_rank": 84, "score": 4, "price_usd": 16.115697634264418, "pct_24h": -2.7683825302729437}, {"id": "allora", "symbol": "ALLO", "name": "Allora", "mcap_rank": 569, "score": 5, "price_usd": 0.1640956791904718, "pct_24h": 79.46617574655623}, {"id": "bitcoin", "symbol": "BTC", "name": "Bitcoin", "mcap_rank": 1, "score": 6, "price_usd": 73507.43363381135, "pct_24h": -1.1368324948488513}, {"id": "ondo-finance", "symbol": "ONDO", "name": "Ondo", "mcap_rank": 48, "score": 7, "price_usd": 0.3683622895003098, "pct_24h": -3.9790128096932706}, {"id": "sui", "symbol": "SUI", "name": "Sui", "mcap_rank": 31, "score": 8, "price_usd": 0.9276217807146538, "pct_24h": -3.308888318187048}, {"id": "zcash", "symbol": "ZEC", "name": "Zcash", "mcap_rank": 14, "score": 9, "price_usd": 545.0311944805833, "pct_24h": 0.6717635615315134}, {"id": "ripple", "symbol": "XRP", "name": "XRP", "mcap_rank": 5, "score": 10, "price_usd": 1.3135108308346994, "pct_24h": 0.6284419305801486}, {"id": "internet-computer", "symbol": "ICP", "name": "Internet Computer", "mcap_rank": 55, "score": 11, "price_usd": 2.723066945887576, "pct_24h": -3.7187720535868447}, {"id": "ethereum", "symbol": "ETH", "name": "Ethereum", "mcap_rank": 2, "score": 12, "price_usd": 2006.5133469934478, "pct_24h": -0.7907467326376422}, {"id": "meta-2-2", "symbol": "META", "name": "MetaDAO", "mcap_rank": 298, "score": 13, "price_usd": 3.976278486001356, "pct_24h": 24.805300819164618}, {"id": "chainlink", "symbol": "LINK", "name": "Chainlink", "mcap_rank": 19, "score": 14, "price_usd": 8.985723876126695, "pct_24h": -1.5057227270439781}], "nfts": [{"id": "normies", "name": "Normies", "symbol": "NORMIES", "contract": 102126225, "score": 0, "native_currency": "eth", "floor_native": 0.61999999, "floor_usd": "0.62 ETH", "floor_24h_pct_native": 20.10863337531657, "h24_volume": "74.77 ETH", "h24_avg_sale_price": "0.73 ETH"}, {"id": "meebits", "name": "Meebits", "symbol": "\u2687", "contract": 28, "score": 1, "native_currency": "eth", "floor_native": 0.3938999, "floor_usd": "0.39 ETH", "floor_24h_pct_native": 6.182132264205171, "h24_volume": "5.71 ETH", "h24_avg_sale_price": "0.44 ETH"}, {"id": "ordinal-maxi-biz-omb", "name": "Ordinal Maxi Biz (OMB)", "symbol": "OMB", "contract": 3256, "score": 2, "native_currency": "btc", "floor_native": 0.0175, "floor_usd": "0.018 BTC", "floor_24h_pct_native": 3.11180681057578, "h24_volume": "0.34 BTC", "h24_avg_sale_price": "0.11 BTC"}, {"id": "bitcoin-shrooms", "name": "Bitcoin Shrooms", "symbol": "BITCOINSHROOMS", "contract": 4161, "score": 3, "native_currency": "btc", "floor_native": 0.335, "floor_usd": "0.34 BTC", "floor_24h_pct_native": 1.596278246543891, "h24_volume": "0.31 BTC", "h24_avg_sale_price": "0.31 BTC"}, {"id": "lilpudgys", "name": "Lil Pudgys", "symbol": "LilPudgys", "contract": 229, "score": 4, "native_currency": "eth", "floor_native": 0.488, "floor_usd": "0.49 ETH", "floor_24h_pct_native": 0.7415947612703104, "h24_volume": "24.64 ETH", "h24_avg_sale_price": "0.48 ETH"}, {"id": "moonbirds", "name": "Moonbirds", "symbol": "MOONBIRD", "contract": 349, "score": 5, "native_currency": "eth", "floor_native": 0.736585, "floor_usd": "0.74 ETH", "floor_24h_pct_native": 0.511878732613164, "h24_volume": "9.93 ETH", "h24_avg_sale_price": "0.76 ETH"}, {"id": "milady-maker", "name": "Milady Maker", "symbol": "MIL", "contract": 317, "score": 6, "native_currency": "eth", "floor_native": 1.379999, "floor_usd": "1.38 ETH", "floor_24h_pct_native": -0.1516876658667419, "h24_volume": "13.35 ETH", "h24_avg_sale_price": "1.33 ETH"}], "categories": [{"id": 314, "name": "Layer 0 (L0)", "slug": "layer-0-l0", "score": 0, "coins_count": "17", "mcap_1h_change": 0.30763687330248085, "mcap": 5076178468.319846, "total_volume": 381400382.003108, "mcap_24h_change_usd": -2.939311480783637}, {"id": 107, "name": "Launchpad", "slug": "launchpad", "score": 1, "coins_count": "198", "mcap_1h_change": 0.2488049396970209, "mcap": 3423651057.2050676, "total_volume": 431513703.0361451, "mcap_24h_change_usd": -6.2615430249498365}, {"id": 72, "name": "Binance Launchpool", "slug": "binance-launchpool", "score": 2, "coins_count": "60", "mcap_1h_change": 0.213429398101255, "mcap": 5751217006.090664, "total_volume": 1109205709.0044346, "mcap_24h_change_usd": -6.932260677524613}, {"id": 113, "name": "Meme", "slug": "meme-token", "score": 3, "coins_count": "5458", "mcap_1h_change": 0.19175591942363798, "mcap": 33408463398.858776, "total_volume": 2803180651.6235366, "mcap_24h_change_usd": -2.3657261897623223}, {"id": 403, "name": "YZi Labs (Prev. Binance Labs) Portfolio", "slug": "yzi-labs-portfolio", "score": 4, "coins_count": "161", "mcap_1h_change": 0.17040397450479142, "mcap": 11524775665.863739, "total_volume": 2346383671.778363, "mcap_24h_change_usd": -6.344244271593791}, {"id": 10623, "name": "Binance Alpha Spotlight", "slug": "binance-alpha-spotlight", "score": 5, "coins_count": "403", "mcap_1h_change": 0.16913439265897645, "mcap": 21218769958.76147, "total_volume": 3043731932.037461, "mcap_24h_change_usd": -3.500078983141372}]}, {"ts": "2026-05-29T00:30:23.634564Z", "coins": [{"id": "bonk", "symbol": "BONK", "name": "Bonk", "mcap_rank": 107, "score": 0, "price_usd": 5.467233656562984e-06, "pct_24h": -4.802647507169788}, {"id": "aptos", "symbol": "APT", "name": "Aptos", "mcap_rank": 82, "score": 1, "price_usd": 0.9430308481965992, "pct_24h": -0.7254333968301842}, {"id": "stellar", "symbol": "XLM", "name": "Stellar", "mcap_rank": 17, "score": 2, "price_usd": 0.20553376738360044, "pct_24h": 23.324520900007062}, {"id": "hyperliquid", "symbol": "HYPE", "name": "Hyperliquid", "mcap_rank": 11, "score": 3, "price_usd": 61.52130487260641, "pct_24h": 6.416026157709914}, {"id": "pudgy-penguins", "symbol": "PENGU", "name": "Pudgy Penguins", "mcap_rank": 106, "score": 4, "price_usd": 0.007738901106069944, "pct_24h": -4.945612925215293}, {"id": "allora", "symbol": "ALLO", "name": "Allora", "mcap_rank": 573, "score": 5, "price_usd": 0.15772226833158554, "pct_24h": 72.86958010284297}, {"id": "bitcoin", "symbol": "BTC", "name": "Bitcoin", "mcap_rank": 1, "score": 6, "price_usd": 73632.45248956392, "pct_24h": -0.966972524333538}, {"id": "ondo-finance", "symbol": "ONDO", "name": "Ondo", "mcap_rank": 48, "score": 7, "price_usd": 0.3692284427384013, "pct_24h": -3.1028412347909597}, {"id": "venice-token", "symbol": "VVV", "name": "Venice Token", "mcap_rank": 84, "score": 8, "price_usd": 16.16311416754881, "pct_24h": -2.350494293983819}, {"id": "solana", "symbol": "SOL", "name": "Solana", "mcap_rank": 7, "score": 9, "price_usd": 82.18705580709852, "pct_24h": -0.2868766538065203}, {"id": "ethereum", "symbol": "ETH", "name": "Ethereum", "mcap_rank": 2, "score": 10, "price_usd": 2012.5005338996364, "pct_24h": -0.3585115006582525}, {"id": "sui", "symbol": "SUI", "name": "Sui", "mcap_rank": 31, "score": 11, "price_usd": 0.9308556736397721, "pct_24h": -2.788524737571042}, {"id": "solstice", "symbol": "SLX", "name": "Solstice", "mcap_rank": 475, "score": 12, "price_usd": 0.21080364811128505, "pct_24h": 4.145635829542862}, {"id": "xmaquina", "symbol": "DEUS", "name": "XMAQUINA", "mcap_rank": 711, "score": 13, "price_usd": 0.05738580242174087, "pct_24h": 12.956087866869497}, {"id": "pendle", "symbol": "PENDLE", "name": "Pendle", "mcap_rank": 165, "score": 14, "price_usd": 1.4613348857759452, "pct_24h": -7.527836349826936}], "nfts": [{"id": "normies", "name": "Normies", "symbol": "NORMIES", "contract": 102126225, "score": 0, "native_currency": "eth", "floor_native": 0.61999999, "floor_usd": "0.62 ETH", "floor_24h_pct_native": 20.37438989152291, "h24_volume": "74.77 ETH", "h24_avg_sale_price": "0.73 ETH"}, {"id": "meebits", "name": "Meebits", "symbol": "\u2687", "contract": 28, "score": 1, "native_currency": "eth", "floor_native": 0.3938999, "floor_usd": "0.39 ETH", "floor_24h_pct_native": 6.182132264205171, "h24_volume": "5.71 ETH", "h24_avg_sale_price": "0.44 ETH"}, {"id": "ordinal-maxi-biz-omb", "name": "Ordinal Maxi Biz (OMB)", "symbol": "OMB", "contract": 3256, "score": 2, "native_currency": "btc", "floor_native": 0.0175, "floor_usd": "0.018 BTC", "floor_24h_pct_native": 3.11180681057578, "h24_volume": "0.34 BTC", "h24_avg_sale_price": "0.11 BTC"}, {"id": "bitcoin-shrooms", "name": "Bitcoin Shrooms", "symbol": "BITCOINSHROOMS", "contract": 4161, "score": 3, "native_currency": "btc", "floor_native": 0.335, "floor_usd": "0.34 BTC", "floor_24h_pct_native": 1.596278246543891, "h24_volume": "0.31 BTC", "h24_avg_sale_price": "0.31 BTC"}, {"id": "lilpudgys", "name": "Lil Pudgys", "symbol": "LilPudgys", "contract": 229, "score": 4, "native_currency": "eth", "floor_native": 0.488, "floor_usd": "0.49 ETH", "floor_24h_pct_native": 0.7415947612703104, "h24_volume": "24.64 ETH", "h24_avg_sale_price": "0.48 ETH"}, {"id": "moonbirds", "name": "Moonbirds", "symbol": "MOONBIRD", "contract": 349, "score": 5, "native_currency": "eth", "floor_native": 0.736585, "floor_usd": "0.74 ETH", "floor_24h_pct_native": 0.511878732613164, "h24_volume": "9.93 ETH", "h24_avg_sale_price": "0.76 ETH"}, {"id": "milady-maker", "name": "Milady Maker", "symbol": "MIL", "contract": 317, "score": 6, "native_currency": "eth", "floor_native": 1.379999, "floor_usd": "1.38 ETH", "floor_24h_pct_native": -0.1516876658667419, "h24_volume": "13.35 ETH", "h24_avg_sale_price": "1.33 ETH"}], "categories": [{"id": 508, "name": "Binance HODLer Airdrops", "slug": "binance-hodler-airdrops", "score": 0, "coins_count": "45", "mcap_1h_change": 0.569254911712365, "mcap": 2468905801.4557734, "total_volume": 703249564.8176837, "mcap_24h_change_usd": -0.7419798022418882}, {"id": 20748, "name": "Robotics", "slug": "robotics", "score": 1, "coins_count": "43", "mcap_1h_change": 0.38562613058477824, "mcap": 820234525.7056645, "total_volume": 143561848.65843096, "mcap_24h_change_usd": 0.7625334088807227}, {"id": 491, "name": "RWA Protocol", "slug": "rwa-protocol", "score": 2, "coins_count": "86", "mcap_1h_change": 0.3050331889489028, "mcap": 9435085609.996096, "total_volume": 707861914.2714976, "mcap_24h_change_usd": -1.9992806065639401}, {"id": 10623, "name": "Binance Alpha Spotlight", "slug": "binance-alpha-spotlight", "score": 3, "coins_count": "403", "mcap_1h_change": 0.3032542865414496, "mcap": 21247866911.54366, "total_volume": 3068926150.657039, "mcap_24h_change_usd": -1.4420889016840204}, {"id": 65, "name": "Yield Farming", "slug": "yield-farming", "score": 4, "coins_count": "187", "mcap_1h_change": 0.2882812179033137, "mcap": 6029599324.981247, "total_volume": 1065845821.5057008, "mcap_24h_change_usd": -1.9199300482269317}, {"id": 403, "name": "YZi Labs (Prev. Binance Labs) Portfolio", "slug": "yzi-labs-portfolio", "score": 5, "coins_count": "161", "mcap_1h_change": 0.2773608543484482, "mcap": 11564030489.938019, "total_volume": 2339251892.1484637, "mcap_24h_change_usd": -3.120459767277426}]}, {"ts": "2026-05-29T01:00:28.812433Z", "coins": [{"id": "bonk", "symbol": "BONK", "name": "Bonk", "mcap_rank": 108, "score": 0, "price_usd": 5.480607613497845e-06, "pct_24h": -4.706214942169075}, {"id": "aptos", "symbol": "APT", "name": "Aptos", "mcap_rank": 82, "score": 1, "price_usd": 0.9480605774341744, "pct_24h": -0.21605825907931572}, {"id": "hyperliquid", "symbol": "HYPE", "name": "Hyperliquid", "mcap_rank": 11, "score": 2, "price_usd": 61.98259493881428, "pct_24h": 6.6403139855839415}, {"id": "stellar", "symbol": "XLM", "name": "Stellar", "mcap_rank": 17, "score": 3, "price_usd": 0.20109384138558525, "pct_24h": 17.391744042143902}, {"id": "allora", "symbol": "ALLO", "name": "Allora", "mcap_rank": 574, "score": 4, "price_usd": 0.1603838216060882, "pct_24h": 74.24328380749064}, {"id": "pudgy-penguins", "symbol": "PENGU", "name": "Pudgy Penguins", "mcap_rank": 106, "score": 5, "price_usd": 0.007771194069908493, "pct_24h": -4.4290442521206375}, {"id": "sui", "symbol": "SUI", "name": "Sui", "mcap_rank": 31, "score": 6, "price_usd": 0.932706526840436, "pct_24h": -2.5411957043411246}, {"id": "solana", "symbol": "SOL", "name": "Solana", "mcap_rank": 7, "score": 7, "price_usd": 82.30511532894488, "pct_24h": -0.2738692527164558}, {"id": "near", "symbol": "NEAR", "name": "NEAR Protocol", "mcap_rank": 32, "score": 8, "price_usd": 2.4863168588141127, "pct_24h": 0.8868131296201599}, {"id": "ripple", "symbol": "XRP", "name": "XRP", "mcap_rank": 5, "score": 9, "price_usd": 1.314798904678921, "pct_24h": 0.5014597918115231}, {"id": "bitcoin", "symbol": "BTC", "name": "Bitcoin", "mcap_rank": 1, "score": 10, "price_usd": 73712.46494076664, "pct_24h": -0.9500549743962374}, {"id": "zcash", "symbol": "ZEC", "name": "Zcash", "mcap_rank": 13, "score": 11, "price_usd": 558.7669068046015, "pct_24h": 3.7964859766259926}, {"id": "ondo-finance", "symbol": "ONDO", "name": "Ondo", "mcap_rank": 48, "score": 12, "price_usd": 0.3719460189305563, "pct_24h": -2.8534515523883286}, {"id": "venice-token", "symbol": "VVV", "name": "Venice Token", "mcap_rank": 83, "score": 13, "price_usd": 16.347037212424873, "pct_24h": -0.6856709371473855}, {"id": "xmaquina", "symbol": "DEUS", "name": "XMAQUINA", "mcap_rank": 706, "score": 14, "price_usd": 0.058061678433924804, "pct_24h": 14.02134655520155}], "nfts": [{"id": "normies", "name": "Normies", "symbol": "NORMIES", "contract": 102126225, "score": 0, "native_currency": "eth", "floor_native": 0.61999999, "floor_usd": "0.62 ETH", "floor_24h_pct_native": 20.957189852641, "h24_volume": "74.18 ETH", "h24_avg_sale_price": "0.73 ETH"}, {"id": "meebits", "name": "Meebits", "symbol": "\u2687", "contract": 28, "score": 1, "native_currency": "eth", "floor_native": 0.3938999, "floor_usd": "0.39 ETH", "floor_24h_pct_native": 6.182132264205171, "h24_volume": "5.71 ETH", "h24_avg_sale_price": "0.44 ETH"}, {"id": "ordinal-maxi-biz-omb", "name": "Ordinal Maxi Biz (OMB)", "symbol": "OMB", "contract": 3256, "score": 2, "native_currency": "btc", "floor_native": 0.0175, "floor_usd": "0.018 BTC", "floor_24h_pct_native": 3.11180681057578, "h24_volume": "0.34 BTC", "h24_avg_sale_price": "0.11 BTC"}, {"id": "bitcoin-shrooms", "name": "Bitcoin Shrooms", "symbol": "BITCOINSHROOMS", "contract": 4161, "score": 3, "native_currency": "btc", "floor_native": 0.335, "floor_usd": "0.34 BTC", "floor_24h_pct_native": 1.596278246543891, "h24_volume": "0.31 BTC", "h24_avg_sale_price": "0.31 BTC"}, {"id": "lilpudgys", "name": "Lil Pudgys", "symbol": "LilPudgys", "contract": 229, "score": 4, "native_currency": "eth", "floor_native": 0.488, "floor_usd": "0.49 ETH", "floor_24h_pct_native": 0.7415947612703104, "h24_volume": "24.64 ETH", "h24_avg_sale_price": "0.48 ETH"}, {"id": "moonbirds", "name": "Moonbirds", "symbol": "MOONBIRD", "contract": 349, "score": 5, "native_currency": "eth", "floor_native": 0.736585, "floor_usd": "0.74 ETH", "floor_24h_pct_native": 0.511878732613164, "h24_volume": "9.93 ETH", "h24_avg_sale_price": "0.76 ETH"}, {"id": "milady-maker", "name": "Milady Maker", "symbol": "MIL", "contract": 317, "score": 6, "native_currency": "eth", "floor_native": 1.379999, "floor_usd": "1.38 ETH", "floor_24h_pct_native": -0.1516876658667419, "h24_volume": "13.35 ETH", "h24_avg_sale_price": "1.33 ETH"}], "categories": [{"id": 20789, "name": "Decentralized Social Media (DeSOC)", "slug": "decentralized-social-media-desoc", "score": 0, "coins_count": "5", "mcap_1h_change": 0.3236301912629181, "mcap": 38884699.1253516, "total_volume": 13861.97912869658, "mcap_24h_change_usd": 8.393170590157233}, {"id": 102120877, "name": "OpenServ Ecosystem", "slug": "openserv-ecosystem", "score": 1, "coins_count": "5", "mcap_1h_change": 1.7941157868992494, "mcap": 3484724.3572542747, "total_volume": 299140.1024402228, "mcap_24h_change_usd": 7.9646167370026415}, {"id": 347, "name": "Farcaster Ecosystem", "slug": "farcaster-ecosystem", "score": 2, "coins_count": "44", "mcap_1h_change": -1.6658915705561863, "mcap": 54749220.19898545, "total_volume": 13422419.156108584, "mcap_24h_change_usd": 7.535103069608256}, {"id": 82, "name": "Derivatives", "slug": "decentralized-derivatives", "score": 3, "coins_count": "121", "mcap_1h_change": 0.559381979201742, "mcap": 15700633562.264011, "total_volume": 1235225379.0997078, "mcap_24h_change_usd": 6.204778053726705}, {"id": 102120808, "name": "Commodities Meme", "slug": "commodities-meme", "score": 4, "coins_count": "7", "mcap_1h_change": 1.0717348464233338, "mcap": 3186289.3770441087, "total_volume": 484584.197897499, "mcap_24h_change_usd": 5.106764666572451}, {"id": 92, "name": "Perpetuals", "slug": "decentralized-perpetuals", "score": 5, "coins_count": "109", "mcap_1h_change": 0.5666427054411979, "mcap": 18243531751.922928, "total_volume": 1499693997.1091275, "mcap_24h_change_usd": 4.853231015000072}]}, {"ts": "2026-05-29T01:30:23.265447Z", "coins": [{"id": "bonk", "symbol": "BONK", "name": "Bonk", "mcap_rank": 108, "score": 0, "price_usd": 5.478952909019704e-06, "pct_24h": -4.108350323379871}, {"id": "aptos", "symbol": "APT", "name": "Aptos", "mcap_rank": 82, "score": 1, "price_usd": 0.9497392460690123, "pct_24h": 0.45342664226019347}, {"id": "hyperliquid", "symbol": "HYPE", "name": "Hyperliquid", "mcap_rank": 11, "score": 2, "price_usd": 62.015144830102955, "pct_24h": 6.793895846022871}, {"id": "stellar", "symbol": "XLM", "name": "Stellar", "mcap_rank": 18, "score": 3, "price_usd": 0.19797414750428813, "pct_24h": 14.226571245660558}, {"id": "allora", "symbol": "ALLO", "name": "Allora", "mcap_rank": 551, "score": 4, "price_usd": 0.17490532146051013, "pct_24h": 89.73092041507623}, {"id": "near", "symbol": "NEAR", "name": "NEAR Protocol", "mcap_rank": 32, "score": 5, "price_usd": 2.520765992259371, "pct_24h": 3.2780714024866606}, {"id": "bitcoin", "symbol": "BTC", "name": "Bitcoin", "mcap_rank": 1, "score": 6, "price_usd": 73673.1532289063, "pct_24h": -0.7832347548227975}, {"id": "ripple", "symbol": "XRP", "name": "XRP", "mcap_rank": 5, "score": 7, "price_usd": 1.3126579559833853, "pct_24h": 0.8333288806772899}, {"id": "zcash", "symbol": "ZEC", "name": "Zcash", "mcap_rank": 13, "score": 8, "price_usd": 558.6573657403168, "pct_24h": 5.615926051606978}, {"id": "pudgy-penguins", "symbol": "PENGU", "name": "Pudgy Penguins", "mcap_rank": 106, "score": 9, "price_usd": 0.007765614412082002, "pct_24h": -4.083937786514437}, {"id": "bittensor", "symbol": "TAO", "name": "Bittensor", "mcap_rank": 39, "score": 10, "price_usd": 261.8320422703746, "pct_24h": -1.0999694280278436}, {"id": "nexus-4", "symbol": "NEX", "name": "Nexus", "mcap_rank": 182, "score": 11, "price_usd": 3.5102341507235104e-06, "pct_24h": 1.2981519385723979}, {"id": "sui", "symbol": "SUI", "name": "Sui", "mcap_rank": 31, "score": 12, "price_usd": 0.931962021014162, "pct_24h": -1.9431869700395943}, {"id": "ethereum", "symbol": "ETH", "name": "Ethereum", "mcap_rank": 2, "score": 13, "price_usd": 2010.9369823891363, "pct_24h": -0.4508741467312712}, {"id": "solana", "symbol": "SOL", "name": "Solana", "mcap_rank": 7, "score": 14, "price_usd": 82.23257028790579, "pct_24h": -0.10389978651927467}], "nfts": [{"id": "normies", "name": "Normies", "symbol": "NORMIES", "contract": 102126225, "score": 0, "native_currency": "eth", "floor_native": 0.61999998, "floor_usd": "0.62 ETH", "floor_24h_pct_native": 20.92109322408114, "h24_volume": "74.18 ETH", "h24_avg_sale_price": "0.73 ETH"}, {"id": "meebits", "name": "Meebits", "symbol": "\u2687", "contract": 28, "score": 1, "native_currency": "eth", "floor_native": 0.3999, "floor_usd": "0.40 ETH", "floor_24h_pct_native": 7.849896900446073, "h24_volume": "6.11 ETH", "h24_avg_sale_price": "0.44 ETH"}, {"id": "ordinal-maxi-biz-omb", "name": "Ordinal Maxi Biz (OMB)", "symbol": "OMB", "contract": 3256, "score": 2, "native_currency": "btc", "floor_native": 0.0175, "floor_usd": "0.018 BTC", "floor_24h_pct_native": 3.11180681057578, "h24_volume": "0.34 BTC", "h24_avg_sale_price": "0.11 BTC"}, {"id": "bitcoin-shrooms", "name": "Bitcoin Shrooms", "symbol": "BITCOINSHROOMS", "contract": 4161, "score": 3, "native_currency": "btc", "floor_native": 0.335, "floor_usd": "0.34 BTC", "floor_24h_pct_native": 1.596278246543891, "h24_volume": "0.31 BTC", "h24_avg_sale_price": "0.31 BTC"}, {"id": "lilpudgys", "name": "Lil Pudgys", "symbol": "LilPudgys", "contract": 229, "score": 4, "native_currency": "eth", "floor_native": 0.488, "floor_usd": "0.49 ETH", "floor_24h_pct_native": 0.7415947612703104, "h24_volume": "24.64 ETH", "h24_avg_sale_price": "0.48 ETH"}, {"id": "moonbirds", "name": "Moonbirds", "symbol": "MOONBIRD", "contract": 349, "score": 5, "native_currency": "eth", "floor_native": 0.736585, "floor_usd": "0.74 ETH", "floor_24h_pct_native": 0.511878732613164, "h24_volume": "9.93 ETH", "h24_avg_sale_price": "0.76 ETH"}, {"id": "milady-maker", "name": "Milady Maker", "symbol": "MIL", "contract": 317, "score": 6, "native_currency": "eth", "floor_native": 1.379999, "floor_usd": "1.38 ETH", "floor_24h_pct_native": -0.1516876658667419, "h24_volume": "13.35 ETH", "h24_avg_sale_price": "1.33 ETH"}], "categories": [{"id": 264, "name": "DRC-20", "slug": "drc-20", "score": 0, "coins_count": "4", "mcap_1h_change": 126.4015150352996, "mcap": 5464773.407794557, "total_volume": 92.82965124946854, "mcap_24h_change_usd": 83.47218829731493}, {"id": 20789, "name": "Decentralized Social Media (DeSOC)", "slug": "decentralized-social-media-desoc", "score": 1, "coins_count": "5", "mcap_1h_change": 0.09306619495964258, "mcap": 38857611.52098133, "total_volume": 13863.947861262659, "mcap_24h_change_usd": 8.317662449746509}, {"id": 102120877, "name": "OpenServ Ecosystem", "slug": "openserv-ecosystem", "score": 2, "coins_count": "5", "mcap_1h_change": 0.32525701484696956, "mcap": 3466272.422281156, "total_volume": 299556.97206921165, "mcap_24h_change_usd": 7.39293419250476}, {"id": 347, "name": "Farcaster Ecosystem", "slug": "farcaster-ecosystem", "score": 3, "coins_count": "44", "mcap_1h_change": -1.5497753649070267, "mcap": 54634485.9302017, "total_volume": 13884066.072697965, "mcap_24h_change_usd": 7.309748966400314}, {"id": 82, "name": "Derivatives", "slug": "decentralized-derivatives", "score": 4, "coins_count": "121", "mcap_1h_change": 0.9096318718234294, "mcap": 15733921539.148077, "total_volume": 1244908942.5320573, "mcap_24h_change_usd": 6.429949998719223}, {"id": 92, "name": "Perpetuals", "slug": "decentralized-perpetuals", "score": 5, "coins_count": "109", "mcap_1h_change": 1.0768930539276087, "mcap": 18293359211.079315, "total_volume": 1512695019.975664, "mcap_24h_change_usd": 5.139610327781133}]}, {"ts": "2026-05-29T02:00:29.422263Z", "coins": [{"id": "bonk", "symbol": "BONK", "name": "Bonk", "mcap_rank": 108, "score": 0, "price_usd": 5.4591668289981645e-06, "pct_24h": -4.251125765798639}, {"id": "aptos", "symbol": "APT", "name": "Aptos", "mcap_rank": 82, "score": 1, "price_usd": 0.9467255041867684, "pct_24h": 0.25106117303399617}, {"id": "hyperliquid", "symbol": "HYPE", "name": "Hyperliquid", "mcap_rank": 11, "score": 2, "price_usd": 61.65517932557915, "pct_24h": 6.095161821845085}, {"id": "pudgy-penguins", "symbol": "PENGU", "name": "Pudgy Penguins", "mcap_rank": 107, "score": 3, "price_usd": 0.007716413842461201, "pct_24h": -4.594827482053064}, {"id": "allora", "symbol": "ALLO", "name": "Allora", "mcap_rank": 556, "score": 4, "price_usd": 0.17004516313489204, "pct_24h": 84.93000526679772}, {"id": "stellar", "symbol": "XLM", "name": "Stellar", "mcap_rank": 18, "score": 5, "price_usd": 0.19656290889490094, "pct_24h": 13.014398944520028}, {"id": "bitcoin", "symbol": "BTC", "name": "Bitcoin", "mcap_rank": 1, "score": 6, "price_usd": 73398.8773587485, "pct_24h": -1.1068809254610814}, {"id": "near", "symbol": "NEAR", "name": "NEAR Protocol", "mcap_rank": 32, "score": 7, "price_usd": 2.5368250202758365, "pct_24h": 3.8276383472909172}, {"id": "megaeth", "symbol": "MEGA", "name": "MegaETH", "mcap_rank": 364, "score": 8, "price_usd": 0.0641442703551118, "pct_24h": -5.89335693176806}, {"id": "octra", "symbol": "OCT", "name": "Octra", "mcap_rank": 343, "score": 9, "price_usd": 0.1230081439865601, "pct_24h": 9.51473275563307}, {"id": "sealcoin", "symbol": "QAIT", "name": "SEALCOIN", "mcap_rank": 415, "score": 10, "price_usd": 0.014200303809599272, "pct_24h": -92.51361735053491}, {"id": "perle", "symbol": "PRL", "name": "Perle", "mcap_rank": 662, "score": 11, "price_usd": 0.18004298194819368, "pct_24h": 18.215820415862936}, {"id": "monad", "symbol": "MON", "name": "Monad", "mcap_rank": 150, "score": 12, "price_usd": 0.023726334537891896, "pct_24h": 3.7544210697044447}, {"id": "canton-network", "symbol": "CC", "name": "Canton", "mcap_rank": 22, "score": 13, "price_usd": 0.1539797891103535, "pct_24h": -1.1582849020920396}, {"id": "venice-token", "symbol": "VVV", "name": "Venice Token", "mcap_rank": 84, "score": 14, "price_usd": 16.187377123883035, "pct_24h": -1.1375910967642504}], "nfts": [{"id": "normies", "name": "Normies", "symbol": "NORMIES", "contract": 102126225, "score": 0, "native_currency": "eth", "floor_native": 0.61999998, "floor_usd": "0.62 ETH", "floor_24h_pct_native": 20.79446310902559, "h24_volume": "74.18 ETH", "h24_avg_sale_price": "0.73 ETH"}, {"id": "meebits", "name": "Meebits", "symbol": "\u2687", "contract": 28, "score": 1, "native_currency": "eth", "floor_native": 0.3999, "floor_usd": "0.40 ETH", "floor_24h_pct_native": 7.849896900446073, "h24_volume": "6.11 ETH", "h24_avg_sale_price": "0.44 ETH"}, {"id": "ordinal-maxi-biz-omb", "name": "Ordinal Maxi Biz (OMB)", "symbol": "OMB", "contract": 3256, "score": 2, "native_currency": "btc", "floor_native": 0.0175, "floor_usd": "0.018 BTC", "floor_24h_pct_native": 3.11180681057578, "h24_volume": "0.34 BTC", "h24_avg_sale_price": "0.11 BTC"}, {"id": "bitcoin-shrooms", "name": "Bitcoin Shrooms", "symbol": "BITCOINSHROOMS", "contract": 4161, "score": 3, "native_currency": "btc", "floor_native": 0.335, "floor_usd": "0.34 BTC", "floor_24h_pct_native": 1.596278246543891, "h24_volume": "0.31 BTC", "h24_avg_sale_price": "0.31 BTC"}, {"id": "lilpudgys", "name": "Lil Pudgys", "symbol": "LilPudgys", "contract": 229, "score": 4, "native_currency": "eth", "floor_native": 0.488, "floor_usd": "0.49 ETH", "floor_24h_pct_native": 0.7415947612703104, "h24_volume": "24.64 ETH", "h24_avg_sale_price": "0.48 ETH"}, {"id": "moonbirds", "name": "Moonbirds", "symbol": "MOONBIRD", "contract": 349, "score": 5, "native_currency": "eth", "floor_native": 0.735565, "floor_usd": "0.74 ETH", "floor_24h_pct_native": 0.1997639805419034, "h24_volume": "9.93 ETH", "h24_avg_sale_price": "0.76 ETH"}, {"id": "milady-maker", "name": "Milady Maker", "symbol": "MIL", "contract": 317, "score": 6, "native_currency": "eth", "floor_native": 1.379999, "floor_usd": "1.38 ETH", "floor_24h_pct_native": -0.1516876658667419, "h24_volume": "13.35 ETH", "h24_avg_sale_price": "1.33 ETH"}], "categories": [{"id": 20802, "name": "Privacy Infrastructure", "slug": "privacy-infrastructure", "score": 0, "coins_count": "64", "mcap_1h_change": 0.33940873941983674, "mcap": 11883103691.449675, "total_volume": 1141259967.1213, "mcap_24h_change_usd": -0.7952340355426237}, {"id": 108, "name": "Wallets", "slug": "wallets", "score": 1, "coins_count": "108", "mcap_1h_change": 0.28267567538712407, "mcap": 2800365366.1422563, "total_volume": 103755369.0721925, "mcap_24h_change_usd": -0.9289434216551528}, {"id": 102120809, "name": "Base Native", "slug": "base-native", "score": 2, "coins_count": "573", "mcap_1h_change": -0.05648942114618024, "mcap": 115813290627.53662, "total_volume": 17227363413.57046, "mcap_24h_change_usd": -0.26024618522728943}, {"id": 186, "name": "Real World Assets (RWA)", "slug": "real-world-assets-rwa", "score": 3, "coins_count": "965", "mcap_1h_change": -0.1357508889519569, "mcap": 63938424175.64631, "total_volume": 3981277616.2093625, "mcap_24h_change_usd": 1.5866805240967525}, {"id": 215, "name": "Alleged SEC Securities", "slug": "alleged-sec-securities", "score": 4, "coins_count": "37", "mcap_1h_change": -0.23136273849168326, "mcap": 133411908489.36925, "total_volume": 3564166508.176208, "mcap_24h_change_usd": -2.623129809765156}, {"id": 10623, "name": "Binance Alpha Spotlight", "slug": "binance-alpha-spotlight", "score": 5, "coins_count": "403", "mcap_1h_change": -0.39157344099391794, "mcap": 21217874719.837917, "total_volume": 3039929346.72439, "mcap_24h_change_usd": -1.5812072318243615}]}, {"ts": "2026-05-29T02:30:26.495156Z", "coins": [{"id": "bonk", "symbol": "BONK", "name": "Bonk", "mcap_rank": 108, "score": 0, "price_usd": 5.467197307216692e-06, "pct_24h": -4.112847959001983}, {"id": "aptos", "symbol": "APT", "name": "Aptos", "mcap_rank": 82, "score": 1, "price_usd": 0.9435424731486309, "pct_24h": -0.3236316740963273}, {"id": "allora", "symbol": "ALLO", "name": "Allora", "mcap_rank": 549, "score": 2, "price_usd": 0.1756212835170169, "pct_24h": 91.19154214956086}, {"id": "hyperliquid", "symbol": "HYPE", "name": "Hyperliquid", "mcap_rank": 11, "score": 3, "price_usd": 61.810371345028514, "pct_24h": 6.731539010099254}, {"id": "pudgy-penguins", "symbol": "PENGU", "name": "Pudgy Penguins", "mcap_rank": 107, "score": 4, "price_usd": 0.007728031623757648, "pct_24h": -4.643743468477872}, {"id": "stellar", "symbol": "XLM", "name": "Stellar", "mcap_rank": 18, "score": 5, "price_usd": 0.19715891821173884, "pct_24h": 11.554380609493663}, {"id": "octra", "symbol": "OCT", "name": "Octra", "mcap_rank": 338, "score": 6, "price_usd": 0.12453639402943714, "pct_24h": 34.513325797645535}, {"id": "megaeth", "symbol": "MEGA", "name": "MegaETH", "mcap_rank": 370, "score": 7, "price_usd": 0.06350086221175437, "pct_24h": -7.236978351774375}, {"id": "citrea", "symbol": "CTR", "name": "Citrea", "mcap_rank": 812, "score": 8, "price_usd": 0.019771321135648782, "pct_24h": 29.57890838400843}, {"id": "pi-network", "symbol": "PI", "name": "Pi Network", "mcap_rank": 53, "score": 9, "price_usd": 0.14438650627405716, "pct_24h": -0.43998009606349897}, {"id": "near", "symbol": "NEAR", "name": "NEAR Protocol", "mcap_rank": 32, "score": 10, "price_usd": 2.538348840069004, "pct_24h": 3.8967546046090047}, {"id": "ondo-finance", "symbol": "ONDO", "name": "Ondo", "mcap_rank": 48, "score": 11, "price_usd": 0.3714934785027039, "pct_24h": -1.229596610519279}, {"id": "aerodrome-finance", "symbol": "AERO", "name": "Aerodrome Finance", "mcap_rank": 124, "score": 12, "price_usd": 0.41309665392075196, "pct_24h": -0.04233467458405238}, {"id": "nockchain", "symbol": "NOCK", "name": "Nockchain", "mcap_rank": 306, "score": 13, "price_usd": 0.04483814153222497, "pct_24h": 14.400812661274834}, {"id": "sealcoin", "symbol": "QAIT", "name": "SEALCOIN", "mcap_rank": 399, "score": 14, "price_usd": 0.014852594924692864, "pct_24h": -92.16973027939099}], "nfts": [{"id": "normies", "name": "Normies", "symbol": "NORMIES", "contract": 102126225, "score": 0, "native_currency": "eth", "floor_native": 0.61999998, "floor_usd": "0.62 ETH", "floor_24h_pct_native": 20.9449984488442, "h24_volume": "74.18 ETH", "h24_avg_sale_price": "0.73 ETH"}, {"id": "meebits", "name": "Meebits", "symbol": "\u2687", "contract": 28, "score": 1, "native_currency": "eth", "floor_native": 0.3999, "floor_usd": "0.40 ETH", "floor_24h_pct_native": 9.429974428740332, "h24_volume": "6.11 ETH", "h24_avg_sale_price": "0.44 ETH"}, {"id": "ordinal-maxi-biz-omb", "name": "Ordinal Maxi Biz (OMB)", "symbol": "OMB", "contract": 3256, "score": 2, "native_currency": "btc", "floor_native": 0.0175, "floor_usd": "0.018 BTC", "floor_24h_pct_native": 3.11180681057578, "h24_volume": "0.34 BTC", "h24_avg_sale_price": "0.11 BTC"}, {"id": "bitcoin-shrooms", "name": "Bitcoin Shrooms", "symbol": "BITCOINSHROOMS", "contract": 4161, "score": 3, "native_currency": "btc", "floor_native": 0.335, "floor_usd": "0.34 BTC", "floor_24h_pct_native": 1.596278246543891, "h24_volume": "0.31 BTC", "h24_avg_sale_price": "0.31 BTC"}, {"id": "lilpudgys", "name": "Lil Pudgys", "symbol": "LilPudgys", "contract": 229, "score": 4, "native_currency": "eth", "floor_native": 0.488, "floor_usd": "0.49 ETH", "floor_24h_pct_native": 0.7415947612703104, "h24_volume": "24.64 ETH", "h24_avg_sale_price": "0.48 ETH"}, {"id": "moonbirds", "name": "Moonbirds", "symbol": "MOONBIRD", "contract": 349, "score": 5, "native_currency": "eth", "floor_native": 0.735565, "floor_usd": "0.74 ETH", "floor_24h_pct_native": 0.1997639805419034, "h24_volume": "9.93 ETH", "h24_avg_sale_price": "0.76 ETH"}, {"id": "milady-maker", "name": "Milady Maker", "symbol": "MIL", "contract": 317, "score": 6, "native_currency": "eth", "floor_native": 1.379999, "floor_usd": "1.38 ETH", "floor_24h_pct_native": -0.1516876658667419, "h24_volume": "13.35 ETH", "h24_avg_sale_price": "1.33 ETH"}], "categories": [{"id": 20802, "name": "Privacy Infrastructure", "slug": "privacy-infrastructure", "score": 0, "coins_count": "64", "mcap_1h_change": 0.40396570376882296, "mcap": 11920528473.428165, "total_volume": 1200018185.9797497, "mcap_24h_change_usd": -0.482797416806522}, {"id": 10673, "name": "Chain Abstraction", "slug": "chain-abstraction", "score": 1, "coins_count": "12", "mcap_1h_change": 0.3196451091344905, "mcap": 10112330017.175318, "total_volume": 1075482248.3704453, "mcap_24h_change_usd": -0.12551777532995284}, {"id": 186, "name": "Real World Assets (RWA)", "slug": "real-world-assets-rwa", "score": 2, "coins_count": "965", "mcap_1h_change": 0.10648749065802202, "mcap": 63983740458.38848, "total_volume": 3847578686.07565, "mcap_24h_change_usd": 1.6586799641333454}, {"id": 102120809, "name": "Base Native", "slug": "base-native", "score": 3, "coins_count": "573", "mcap_1h_change": 0.08285735288763024, "mcap": 115911059127.55681, "total_volume": 17165410245.83155, "mcap_24h_change_usd": -0.1760468151030584}, {"id": 291, "name": "Proof of Stake (PoS)", "slug": "proof-of-stake-pos", "score": 4, "coins_count": "153", "mcap_1h_change": 0.013212089725729811, "mcap": 459149146912.5896, "total_volume": 25142537596.25602, "mcap_24h_change_usd": -0.9923737187632122}, {"id": 215, "name": "Alleged SEC Securities", "slug": "alleged-sec-securities", "score": 5, "coins_count": "37", "mcap_1h_change": -0.06858956111421224, "mcap": 133572638253.34778, "total_volume": 3557278951.0773807, "mcap_24h_change_usd": -2.5058137355116217}]}]}