{"date": "2026-06-19", "snapshots": [{"ts": "2026-06-19T00:00:49.711893Z", "coins": [{"id": "autonomi", "symbol": "ANT", "name": "Autonomi", "mcap_rank": 715, "score": 0, "price_usd": 0.07505308507110285, "pct_24h": 11.415797038314029}, {"id": "asteroid-shiba", "symbol": "ASTEROID", "name": "Asteroid Shiba", "mcap_rank": 361, "score": 1, "price_usd": 0.00016729761286801928, "pct_24h": 81.41621626062197}, {"id": "siren-2", "symbol": "SIREN", "name": "Siren", "mcap_rank": 299, "score": 2, "price_usd": 0.11779833760309391, "pct_24h": 148.19688518897823}, {"id": "lab", "symbol": "LAB", "name": "LAB", "mcap_rank": 22, "score": 3, "price_usd": 17.52398137586412, "pct_24h": 32.54907247364887}, {"id": "pudgy-penguins", "symbol": "PENGU", "name": "Pudgy Penguins", "mcap_rank": 114, "score": 4, "price_usd": 0.006728040855979992, "pct_24h": -1.9074652633989113}, {"id": "venice-token", "symbol": "VVV", "name": "Venice Token", "mcap_rank": 86, "score": 5, "price_usd": 14.385878592017121, "pct_24h": -8.749081538955167}, {"id": "bitcoin", "symbol": "BTC", "name": "Bitcoin", "mcap_rank": 1, "score": 6, "price_usd": 62840.2024355139, "pct_24h": -2.472594548985129}, {"id": "humanity", "symbol": "H", "name": "Humanity", "mcap_rank": 117, "score": 7, "price_usd": 0.22325057235528056, "pct_24h": -2.5540471928880843}, {"id": "ethereum", "symbol": "ETH", "name": "Ethereum", "mcap_rank": 2, "score": 8, "price_usd": 1708.262803652492, "pct_24h": -2.2501617524458357}, {"id": "hyperliquid", "symbol": "HYPE", "name": "Hyperliquid", "mcap_rank": 10, "score": 9, "price_usd": 68.01211317730868, "pct_24h": -4.530050510287438}, {"id": "collector-crypt", "symbol": "CARDS", "name": "Collector Crypt", "mcap_rank": 308, "score": 10, "price_usd": 0.3143250831256406, "pct_24h": 33.65174571343134}, {"id": "aerodrome-finance", "symbol": "AERO", "name": "Aerodrome Finance", "mcap_rank": 115, "score": 11, "price_usd": 0.4389223169556393, "pct_24h": -0.15089365057955637}, {"id": "uniswap", "symbol": "UNI", "name": "Uniswap", "mcap_rank": 44, "score": 12, "price_usd": 3.173937859381199, "pct_24h": -1.6967742148519938}, {"id": "synapse-2", "symbol": "SYN", "name": "Synapse", "mcap_rank": 639, "score": 13, "price_usd": 0.13839505460148252, "pct_24h": 66.98565920973103}, {"id": "algorand", "symbol": "ALGO", "name": "Algorand", "mcap_rank": 76, "score": 14, "price_usd": 0.09594511735368082, "pct_24h": -2.4799291854324474}], "nfts": [{"id": "ordinal-maxi-biz-omb", "name": "Ordinal Maxi Biz (OMB)", "symbol": "OMB", "contract": 3256, "score": 0, "native_currency": "btc", "floor_native": 0.0175, "floor_usd": "0.018 BTC", "floor_24h_pct_native": 3.11180681057578, "h24_volume": "0.34 BTC", "h24_avg_sale_price": "0.11 BTC"}, {"id": "lilpudgys", "name": "Lil Pudgys", "symbol": "LilPudgys", "contract": 229, "score": 1, "native_currency": "eth", "floor_native": 0.5096, "floor_usd": "0.51 ETH", "floor_24h_pct_native": 2.581825327401526, "h24_volume": "18.22 ETH", "h24_avg_sale_price": "0.51 ETH"}, {"id": "bitcoin-shrooms", "name": "Bitcoin Shrooms", "symbol": "BITCOINSHROOMS", "contract": 4161, "score": 2, "native_currency": "btc", "floor_native": 0.335, "floor_usd": "0.34 BTC", "floor_24h_pct_native": 1.596278246543891, "h24_volume": "0.31 BTC", "h24_avg_sale_price": "0.31 BTC"}, {"id": "bored-ape-yacht-club", "name": "Bored Ape Yacht Club", "symbol": "BAYC", "contract": 20, "score": 3, "native_currency": "eth", "floor_native": 9.3098999999999, "floor_usd": "9.31 ETH", "floor_24h_pct_native": 0.8485524830281411, "h24_volume": "106.67 ETH", "h24_avg_sale_price": "9.70 ETH"}, {"id": "azuki", "name": "Azuki", "symbol": "AZUKI", "contract": 246, "score": 4, "native_currency": "eth", "floor_native": 0.84, "floor_usd": "0.84 ETH", "floor_24h_pct_native": -0.97775223686814, "h24_volume": "13.31 ETH", "h24_avg_sale_price": "0.89 ETH"}, {"id": "pudgy-penguins", "name": "Pudgy Penguins", "symbol": "PPG", "contract": 38, "score": 5, "native_currency": "eth", "floor_native": 4.515, "floor_usd": "4.52 ETH", "floor_24h_pct_native": -1.705245382372698, "h24_volume": "209.66 ETH", "h24_avg_sale_price": "4.56 ETH"}, {"id": "cryptopunks", "name": "CryptoPunks", "symbol": "PUNK", "contract": 270, "score": 6, "native_currency": "eth", "floor_native": 32.7, "floor_usd": "32.70 ETH", "floor_24h_pct_native": -2.180111174970006, "h24_volume": "197.00 ETH", "h24_avg_sale_price": "-"}], "categories": [{"id": 20747, "name": "Trading Card RWA Platform", "slug": "trading-card-rwa-platform", "score": 0, "coins_count": "7", "mcap_1h_change": 7.960349041493782, "mcap": 116934654.5926318, "total_volume": 15736769.612343393, "mcap_24h_change_usd": 13.851911547523448}, {"id": 294, "name": "Index Coop Defi Index", "slug": "defi-pulse-index-dpi", "score": 1, "coins_count": "10", "mcap_1h_change": 1.9741051361668083, "mcap": 3688746826.7625093, "total_volume": 652547541.5008168, "mcap_24h_change_usd": -3.1167522075143554}, {"id": 70, "name": "Automated Market Maker (AMM)", "slug": "automated-market-maker-amm", "score": 2, "coins_count": "77", "mcap_1h_change": 1.6028683592426083, "mcap": 4696856424.211395, "total_volume": 747828568.3421971, "mcap_24h_change_usd": -4.022050164167268}, {"id": 20793, "name": "CoinList Launchpad", "slug": "coinlist-launchpad", "score": 3, "coins_count": "71", "mcap_1h_change": 0.31404511487813713, "mcap": 48655254395.10845, "total_volume": 3320169771.420546, "mcap_24h_change_usd": -4.744585344339073}, {"id": 203, "name": "Bridge Governance Tokens", "slug": "bridge-governance-tokens", "score": 4, "coins_count": "21", "mcap_1h_change": 0.2631912270118024, "mcap": 401906759.1569109, "total_volume": 151139111.42525962, "mcap_24h_change_usd": 2.9595805649021254}, {"id": 508, "name": "Binance HODLer Airdrops", "slug": "binance-hodler-airdrops", "score": 5, "coins_count": "46", "mcap_1h_change": 0.25837997036097093, "mcap": 2262531338.6467867, "total_volume": 665192509.512467, "mcap_24h_change_usd": -3.2984496412937205}]}, {"ts": "2026-06-19T00:30:41.288313Z", "coins": [{"id": "autonomi", "symbol": "ANT", "name": "Autonomi", "mcap_rank": 716, "score": 0, "price_usd": 0.075036836666913, "pct_24h": 10.46755960174573}, {"id": "asteroid-shiba", "symbol": "ASTEROID", "name": "Asteroid Shiba", "mcap_rank": 347, "score": 1, "price_usd": 0.00017174978974357293, "pct_24h": 85.65772414723891}, {"id": "siren-2", "symbol": "SIREN", "name": "Siren", "mcap_rank": 302, "score": 2, "price_usd": 0.11761625171567926, "pct_24h": 145.72742489645802}, {"id": "lab", "symbol": "LAB", "name": "LAB", "mcap_rank": 22, "score": 3, "price_usd": 17.981651043801982, "pct_24h": 38.019519504904835}, {"id": "pudgy-penguins", "symbol": "PENGU", "name": "Pudgy Penguins", "mcap_rank": 114, "score": 4, "price_usd": 0.006743364814044299, "pct_24h": -2.515765038160391}, {"id": "collector-crypt", "symbol": "CARDS", "name": "Collector Crypt", "mcap_rank": 308, "score": 5, "price_usd": 0.3140388096300852, "pct_24h": 33.808238040478194}, {"id": "ethereum", "symbol": "ETH", "name": "Ethereum", "mcap_rank": 2, "score": 6, "price_usd": 1708.8518222392443, "pct_24h": -2.6097798472393374}, {"id": "venice-token", "symbol": "VVV", "name": "Venice Token", "mcap_rank": 86, "score": 7, "price_usd": 14.358348246788104, "pct_24h": -9.590362569540174}, {"id": "aave", "symbol": "AAVE", "name": "Aave", "mcap_rank": 63, "score": 8, "price_usd": 74.67925990031952, "pct_24h": 0.8043945247035019}, {"id": "aerodrome-finance", "symbol": "AERO", "name": "Aerodrome Finance", "mcap_rank": 115, "score": 9, "price_usd": 0.4400811832609418, "pct_24h": -1.5052851058296453}, {"id": "ripple", "symbol": "XRP", "name": "XRP", "mcap_rank": 6, "score": 10, "price_usd": 1.1435697272331136, "pct_24h": -3.70785194887096}, {"id": "bittensor", "symbol": "TAO", "name": "Bittensor", "mcap_rank": 41, "score": 11, "price_usd": 234.92782608875459, "pct_24h": -4.9336119308192625}, {"id": "zcash", "symbol": "ZEC", "name": "Zcash", "mcap_rank": 16, "score": 12, "price_usd": 453.92569732553545, "pct_24h": -5.62389654894753}, {"id": "bitcoin", "symbol": "BTC", "name": "Bitcoin", "mcap_rank": 1, "score": 13, "price_usd": 62809.86269046846, "pct_24h": -2.7970259443436807}, {"id": "hyperliquid", "symbol": "HYPE", "name": "Hyperliquid", "mcap_rank": 10, "score": 14, "price_usd": 67.88698402263401, "pct_24h": -5.513386590232595}], "nfts": [{"id": "ordinal-maxi-biz-omb", "name": "Ordinal Maxi Biz (OMB)", "symbol": "OMB", "contract": 3256, "score": 0, "native_currency": "btc", "floor_native": 0.0175, "floor_usd": "0.018 BTC", "floor_24h_pct_native": 3.11180681057578, "h24_volume": "0.34 BTC", "h24_avg_sale_price": "0.11 BTC"}, {"id": "lilpudgys", "name": "Lil Pudgys", "symbol": "LilPudgys", "contract": 229, "score": 1, "native_currency": "eth", "floor_native": 0.5096, "floor_usd": "0.51 ETH", "floor_24h_pct_native": 1.729413754644159, "h24_volume": "19.79 ETH", "h24_avg_sale_price": "0.51 ETH"}, {"id": "bitcoin-shrooms", "name": "Bitcoin Shrooms", "symbol": "BITCOINSHROOMS", "contract": 4161, "score": 2, "native_currency": "btc", "floor_native": 0.335, "floor_usd": "0.34 BTC", "floor_24h_pct_native": 1.596278246543891, "h24_volume": "0.31 BTC", "h24_avg_sale_price": "0.31 BTC"}, {"id": "bored-ape-yacht-club", "name": "Bored Ape Yacht Club", "symbol": "BAYC", "contract": 20, "score": 3, "native_currency": "eth", "floor_native": 9.2989999999999, "floor_usd": "9.30 ETH", "floor_24h_pct_native": 0.06248970128115595, "h24_volume": "106.67 ETH", "h24_avg_sale_price": "9.70 ETH"}, {"id": "azuki", "name": "Azuki", "symbol": "AZUKI", "contract": 246, "score": 4, "native_currency": "eth", "floor_native": 0.84, "floor_usd": "0.84 ETH", "floor_24h_pct_native": -1.440475418579905, "h24_volume": "13.31 ETH", "h24_avg_sale_price": "0.89 ETH"}, {"id": "pudgy-penguins", "name": "Pudgy Penguins", "symbol": "PPG", "contract": 38, "score": 5, "native_currency": "eth", "floor_native": 4.515, "floor_usd": "4.52 ETH", "floor_24h_pct_native": -1.753219992129269, "h24_volume": "209.66 ETH", "h24_avg_sale_price": "4.56 ETH"}, {"id": "hypurr-hyperevm", "name": "Hypurr", "symbol": "HYPURR", "contract": 26031, "score": 6, "native_currency": "hype", "floor_native": 245.0, "floor_usd": "245.00 HYPE", "floor_24h_pct_native": -2.919954926745739, "h24_volume": "164.09 HYPE", "h24_avg_sale_price": "9.12 HYPE"}], "categories": [{"id": 20747, "name": "Trading Card RWA Platform", "slug": "trading-card-rwa-platform", "score": 0, "coins_count": "7", "mcap_1h_change": 7.6480077967314, "mcap": 116606518.15075801, "total_volume": 16232282.919573676, "mcap_24h_change_usd": 16.965227721535662}, {"id": 294, "name": "Index Coop Defi Index", "slug": "defi-pulse-index-dpi", "score": 1, "coins_count": "10", "mcap_1h_change": 1.8325184135711337, "mcap": 3695546353.3698807, "total_volume": 665334614.253491, "mcap_24h_change_usd": -0.7130766903433593}, {"id": 70, "name": "Automated Market Maker (AMM)", "slug": "automated-market-maker-amm", "score": 2, "coins_count": "77", "mcap_1h_change": 1.5539173717609223, "mcap": 4708252010.772973, "total_volume": 751262223.5428755, "mcap_24h_change_usd": -2.0597676505729856}, {"id": 10623, "name": "Binance Alpha Spotlight", "slug": "binance-alpha-spotlight", "score": 3, "coins_count": "403", "mcap_1h_change": 1.005943351616061, "mcap": 25562252066.2915, "total_volume": 2114617144.583489, "mcap_24h_change_usd": 4.149748500328191}, {"id": 344, "name": "Stablecoin Issuer", "slug": "stablecoin-issuer", "score": 4, "coins_count": "43", "mcap_1h_change": 0.8630544475302265, "mcap": 6225782164.111007, "total_volume": 551319681.9029644, "mcap_24h_change_usd": -1.265357161148141}, {"id": 102120869, "name": "Venice Ecosystem", "slug": "venice-ecosystem", "score": 5, "coins_count": "6", "mcap_1h_change": 0.6029450979996612, "mcap": 764244636.8023223, "total_volume": 34240873.22574834, "mcap_24h_change_usd": -8.114904322684437}]}]}